{
  "caption": "Front End Engineer at Meta",
  "sections": [
    {
      "title": "Articles",
      "items": [
        {
          "title": "Let's Build React Context in Vanilla JS.",
          "url": "https://www.smashingmagazine.com/2022/08/react-context-propagation-javascript",
          "extra": "Smashing Magazine"
        },
        {
          "title": "Dead Simple React Validations with Vest.",
          "url": "https://dev.to/ealush/dead-simple-form-validation-with-vest-5gf8"
        },
        {
          "title": "Fight Validations Spaghetti with Vest.",
          "url": "https://dev.to/ealush/fight-validations-spaghetti-with-vest-3i8j"
        },
        {
          "title": "Creating APIs for the human developer",
          "url": "https://medium.com/fiverr-engineering/creating-apis-for-the-human-developer-c0f51a6d9366"
        },
        {
          "title": "Writing a JS Proxy based assertion function",
          "url": "https://medium.com/fiverr-engineering/writing-a-js-proxy-based-assertion-function-5a7359df9f9b"
        },
        {
          "title": "Introducing Passable",
          "url": "https://medium.com/fiverr-engineering/introducing-passable-45250548afd1"
        }
      ]
    },
    {
      "title": "Videos",
      "items": [
        {
          "title": "Up Your Form Validation Game with Vest",
          "url": "https://www.youtube.com/watch?v=X2PuiawaGV4",
          "extra": "Svelte Summit | Fall 2021"
        },
        {
          "title": "Vue Form Validations with Vest",
          "url": "https://portal.gitnation.org/contents/vue-form-validations-with-vest",
          "extra": "Vue.js London"
        },
        {
          "title": "What you need to know about contributing to open source",
          "url": "https://www.youtube.com/watch?v=2D0LmCtVTSk",
          "extra": "(Hebrew)"
        },
        {
          "title": "It can't be that easy! Form validations with Vest",
          "url": "https://www.youtube.com/watch?v=mL9ocOBg2y4",
          "extra": "(Conf42)"
        },
        {
          "title": "Vest Demo",
          "url": "https://twitter.com/AlushEvyatar/status/1281297006070284289"
        },
        {
          "title": "Rethinking form validations",
          "url": "https://www.youtube.com/watch?v=_R5WfSXBruk",
          "extra": "(Hebrew)"
        }
      ]
    },
    {
      "title": "Interviews",
      "items": [
        {
          "title": "Wearing a Vest is in Style",
          "url": "https://webrush.io/episodes/episode-188-wearing-a-vest-is-in-style-with-evyatar-alush",
          "extra": "Web Rush Podcast"
        },
        {
          "title": "Every Question Answered",
          "url": "https://fedcast.co.il/%D7%9C%D7%9B%D7%9C_%D7%A9%D7%90%D7%9C%D7%94_%D7%AA%D7%A9%D7%95%D7%91%D7%94/1505/%D7%9C%D7%9B%D7%9C-%D7%A9%D7%90%D7%9C%D7%94-%D7%AA%D7%A9%D7%95%D7%91%D7%94-%D7%A2%D7%9D-%D7%90%D7%91%D7%99%D7%AA%D7%A8-%D7%90%D7%9C%D7%95%D7%A9/",
          "extra": "FED Cast IL (Hebrew)"
        },
        {
          "title": "API Design IRL",
          "url": "https://open.spotify.com/episode/2mrcevFlUKAxcUdQ4pyTYj",
          "extra": "Open Source Podcast (Hebrew)"
        },
        {
          "title": "Playing it close to the Vest",
          "url": "https://changelog.com/jsparty/213",
          "extra": "JS Party"
        },
        {
          "title": "Vest with Evyatar Alush",
          "url": "https://podrocket.logrocket.com/vest",
          "extra": "PodRocket by LogRocket"
        },
        {
          "title": "DX is UX",
          "url": "https://anchor.fm/frontend-greatness/episodes/DX-is-UX-With-Evyatar-e12tco9",
          "extra": "Frontend Greatness Podcast"
        },
        {
          "title": "Form Validations and Open Source",
          "url": "https://reactroundup.com/172",
          "extra": "React Roundup Podcast"
        }
      ]
    }
  ]
}
